{
  "meta": {
    "tag": "full",
    "NS": [
      16,
      32,
      48
    ],
    "M": 300,
    "thetas": [
      "0",
      "pi/8",
      "pi/4",
      "3pi/8",
      "pi/2",
      "5pi/8",
      "3pi/4",
      "7pi/8",
      "pi"
    ],
    "theta_vals": [
      0.0,
      0.39269908169872414,
      0.7853981633974483,
      1.1780972450961724,
      1.5707963267948966,
      1.9634954084936207,
      2.356194490192345,
      2.748893571891069,
      3.141592653589793
    ],
    "T_mid": 0.05,
    "T_low": 0.02,
    "params": {
      "k_s": 20.0,
      "k_b": 2.0,
      "k_f": 1.0,
      "k_c": 2.0,
      "ell": 1.0
    },
    "commit_base": "81cc7da",
    "note": "\u0421\u042b\u0420\u042b\u0415 \u0442\u0430\u0431\u043b\u0438\u0446\u044b AX; \u0444\u043b\u0438\u043f/\u0444\u0438\u0442\u044b \u2014 \u041f\u041e\u0421\u041b\u0415 \u043a\u043e\u043c\u043c\u0438\u0442\u0430"
  },
  "AX": {
    "N16|even|0": {
      "table": {
        "pp": 203,
        "pm": 38,
        "mp": 45,
        "mm": 14,
        "degen": 0
      },
      "E_raw": 0.44666666666666666,
      "sigma": 0.05165555436055542,
      "n_valid": 300,
      "rej_per_step": 5.555555555555555e-07
    },
    "N16|even|pi/8": {
      "table": {
        "pp": 197,
        "pm": 49,
        "mp": 39,
        "mm": 15,
        "degen": 0
      },
      "E_raw": 0.41333333333333333,
      "sigma": 0.052572348738208874,
      "n_valid": 300,
      "rej_per_step": 0.0
    },
    "N16|even|pi/4": {
      "table": {
        "pp": 178,
        "pm": 76,
        "mp": 31,
        "mm": 15,
        "degen": 0
      },
      "E_raw": 0.2866666666666667,
      "sigma": 0.055311910176809184,
      "n_valid": 300,
      "rej_per_step": 0.0
    },
    "N16|even|3pi/8": {
      "table": {
        "pp": 150,
        "pm": 95,
        "mp": 40,
        "mm": 15,
        "degen": 0
      },
      "E_raw": 0.1,
      "sigma": 0.05744562646538029,
      "n_valid": 300,
      "rej_per_step": 1.111111111111111e-06
    },
    "N16|even|pi/2": {
      "table": {
        "pp": 125,
        "pm": 108,
        "mp": 36,
        "mm": 31,
        "degen": 0
      },
      "E_raw": 0.04,
      "sigma": 0.057688820407423826,
      "n_valid": 300,
      "rej_per_step": 0.0
    },
    "N16|even|5pi/8": {
      "table": {
        "pp": 85,
        "pm": 164,
        "mp": 21,
        "mm": 30,
        "degen": 0
      },
      "E_raw": -0.23333333333333334,
      "sigma": 0.05614135598515458,
      "n_valid": 300,
      "rej_per_step": 0.0
    },
    "N16|even|3pi/4": {
      "table": {
        "pp": 85,
        "pm": 168,
        "mp": 14,
        "mm": 33,
        "degen": 0
      },
      "E_raw": -0.21333333333333335,
      "sigma": 0.056405936120497366,
      "n_valid": 300,
      "rej_per_step": 0.0
    },
    "N16|even|7pi/8": {
      "table": {
        "pp": 45,
        "pm": 197,
        "mp": 13,
        "mm": 45,
        "degen": 0
      },
      "E_raw": -0.4,
      "sigma": 0.05291502622129181,
      "n_valid": 300,
      "rej_per_step": 0.0
    },
    "N16|even|pi": {
      "table": {
        "pp": 45,
        "pm": 185,
        "mp": 16,
        "mm": 54,
        "degen": 0
      },
      "E_raw": -0.34,
      "sigma": 0.05429548784199291,
      "n_valid": 300,
      "rej_per_step": 0.0
    },
    "N16|odd|0": {
      "table": {
        "pp": 208,
        "pm": 46,
        "mp": 35,
        "mm": 11,
        "degen": 0
      },
      "E_raw": 0.46,
      "sigma": 0.05126402247190519,
      "n_valid": 300,
      "rej_per_step": 0.0
    },
    "N16|odd|pi/8": {
      "table": {
        "pp": 200,
        "pm": 42,
        "mp": 53,
        "mm": 5,
        "degen": 0
      },
      "E_raw": 0.36666666666666664,
      "sigma": 0.05371391984565254,
      "n_valid": 300,
      "rej_per_step": 0.0
    },
    "N16|odd|pi/4": {
      "table": {
        "pp": 160,
        "pm": 75,
        "mp": 47,
        "mm": 18,
        "degen": 0
      },
      "E_raw": 0.18666666666666668,
      "sigma": 0.05672023611714946,
      "n_valid": 300,
      "rej_per_step": 1.6666666666666667e-06
    },
    "N16|odd|3pi/8": {
      "table": {
        "pp": 162,
        "pm": 71,
        "mp": 40,
        "mm": 27,
        "degen": 0
      },
      "E_raw": 0.26,
      "sigma": 0.055749439459065415,
      "n_valid": 300,
      "rej_per_step": 5.555555555555555e-07
    },
    "N16|odd|pi/2": {
      "table": {
        "pp": 117,
        "pm": 118,
        "mp": 32,
        "mm": 33,
        "degen": 0
      },
      "E_raw": 0.0,
      "sigma": 0.05773502691896258,
      "n_valid": 300,
      "rej_per_step": 5.555555555555555e-07
    },
    "N16|odd|5pi/8": {
      "table": {
        "pp": 89,
        "pm": 150,
        "mp": 23,
        "mm": 38,
        "degen": 0
      },
      "E_raw": -0.15333333333333332,
      "sigma": 0.057052282714743004,
      "n_valid": 300,
      "rej_per_step": 0.0
    },
    "N16|odd|3pi/4": {
      "table": {
        "pp": 73,
        "pm": 157,
        "mp": 18,
        "mm": 52,
        "degen": 0
      },
      "E_raw": -0.16666666666666666,
      "sigma": 0.0569275042553311,
      "n_valid": 300,
      "rej_per_step": 0.0
    },
    "N16|odd|7pi/8": {
      "table": {
        "pp": 71,
        "pm": 168,
        "mp": 15,
        "mm": 46,
        "degen": 0
      },
      "E_raw": -0.22,
      "sigma": 0.05632051136131489,
      "n_valid": 300,
      "rej_per_step": 5.555555555555555e-07
    },
    "N16|odd|pi": {
      "table": {
        "pp": 44,
        "pm": 188,
        "mp": 19,
        "mm": 49,
        "degen": 0
      },
      "E_raw": -0.38,
      "sigma": 0.05340411969127475,
      "n_valid": 300,
      "rej_per_step": 1.6666666666666667e-06
    },
    "N32|even|0": {
      "table": {
        "pp": 186,
        "pm": 55,
        "mp": 51,
        "mm": 8,
        "degen": 0
      },
      "E_raw": 0.29333333333333333,
      "sigma": 0.05519527623373687,
      "n_valid": 300,
      "rej_per_step": 0.0
    },
    "N32|even|pi/8": {
      "table": {
        "pp": 194,
        "pm": 58,
        "mp": 39,
        "mm": 9,
        "degen": 0
      },
      "E_raw": 0.35333333333333333,
      "sigma": 0.054010972822058904,
      "n_valid": 300,
      "rej_per_step": 0.0
    },
    "N32|even|pi/4": {
      "table": {
        "pp": 169,
        "pm": 73,
        "mp": 37,
        "mm": 21,
        "degen": 0
      },
      "E_raw": 0.26666666666666666,
      "sigma": 0.05564437344688406,
      "n_valid": 300,
      "rej_per_step": 0.0
    },
    "N32|even|3pi/8": {
      "table": {
        "pp": 147,
        "pm": 87,
        "mp": 44,
        "mm": 22,
        "degen": 0
      },
      "E_raw": 0.12666666666666668,
      "sigma": 0.057269990849063805,
      "n_valid": 300,
      "rej_per_step": 5.555555555555555e-07
    },
    "N32|even|pi/2": {
      "table": {
        "pp": 131,
        "pm": 111,
        "mp": 29,
        "mm": 29,
        "degen": 0
      },
      "E_raw": 0.06666666666666667,
      "sigma": 0.05760658398584764,
      "n_valid": 300,
      "rej_per_step": 0.0
    },
    "N32|even|5pi/8": {
      "table": {
        "pp": 91,
        "pm": 149,
        "mp": 13,
        "mm": 47,
        "degen": 0
      },
      "E_raw": -0.08,
      "sigma": 0.05754997827975264,
      "n_valid": 300,
      "rej_per_step": 0.0
    },
    "N32|even|3pi/4": {
      "table": {
        "pp": 58,
        "pm": 169,
        "mp": 13,
        "mm": 60,
        "degen": 0
      },
      "E_raw": -0.21333333333333335,
      "sigma": 0.056405936120497366,
      "n_valid": 300,
      "rej_per_step": 0.0
    },
    "N32|even|7pi/8": {
      "table": {
        "pp": 49,
        "pm": 195,
        "mp": 10,
        "mm": 46,
        "degen": 0
      },
      "E_raw": -0.36666666666666664,
      "sigma": 0.05371391984565254,
      "n_valid": 300,
      "rej_per_step": 0.0
    },
    "N32|even|pi": {
      "table": {
        "pp": 51,
        "pm": 187,
        "mp": 13,
        "mm": 49,
        "degen": 0
      },
      "E_raw": -0.3333333333333333,
      "sigma": 0.05443310539518174,
      "n_valid": 300,
      "rej_per_step": 0.0
    },
    "N32|odd|0": {
      "table": {
        "pp": 205,
        "pm": 41,
        "mp": 45,
        "mm": 9,
        "degen": 0
      },
      "E_raw": 0.4266666666666667,
      "sigma": 0.05221607528834888,
      "n_valid": 300,
      "rej_per_step": 0.0
    },
    "N32|odd|pi/8": {
      "table": {
        "pp": 195,
        "pm": 49,
        "mp": 48,
        "mm": 8,
        "degen": 0
      },
      "E_raw": 0.35333333333333333,
      "sigma": 0.054010972822058904,
      "n_valid": 300,
      "rej_per_step": 0.0
    },
    "N32|odd|pi/4": {
      "table": {
        "pp": 173,
        "pm": 71,
        "mp": 48,
        "mm": 8,
        "degen": 0
      },
      "E_raw": 0.20666666666666667,
      "sigma": 0.05648860914346328,
      "n_valid": 300,
      "rej_per_step": 0.0
    },
    "N32|odd|3pi/8": {
      "table": {
        "pp": 144,
        "pm": 102,
        "mp": 33,
        "mm": 21,
        "degen": 0
      },
      "E_raw": 0.1,
      "sigma": 0.05744562646538029,
      "n_valid": 300,
      "rej_per_step": 5.555555555555555e-07
    },
    "N32|odd|pi/2": {
      "table": {
        "pp": 120,
        "pm": 124,
        "mp": 35,
        "mm": 21,
        "degen": 0
      },
      "E_raw": -0.06,
      "sigma": 0.05763101017102974,
      "n_valid": 300,
      "rej_per_step": 5.555555555555555e-07
    },
    "N32|odd|5pi/8": {
      "table": {
        "pp": 74,
        "pm": 149,
        "mp": 30,
        "mm": 47,
        "degen": 0
      },
      "E_raw": -0.19333333333333333,
      "sigma": 0.056645747772809396,
      "n_valid": 300,
      "rej_per_step": 0.0
    },
    "N32|odd|3pi/4": {
      "table": {
        "pp": 71,
        "pm": 162,
        "mp": 21,
        "mm": 46,
        "degen": 0
      },
      "E_raw": -0.22,
      "sigma": 0.05632051136131489,
      "n_valid": 300,
      "rej_per_step": 5.555555555555555e-07
    },
    "N32|odd|7pi/8": {
      "table": {
        "pp": 43,
        "pm": 184,
        "mp": 12,
        "mm": 61,
        "degen": 0
      },
      "E_raw": -0.30666666666666664,
      "sigma": 0.05495317872381772,
      "n_valid": 300,
      "rej_per_step": 1.111111111111111e-06
    },
    "N32|odd|pi": {
      "table": {
        "pp": 47,
        "pm": 198,
        "mp": 9,
        "mm": 46,
        "degen": 0
      },
      "E_raw": -0.38,
      "sigma": 0.05340411969127475,
      "n_valid": 300,
      "rej_per_step": 0.0
    },
    "N48|even|0": {
      "table": {
        "pp": 192,
        "pm": 51,
        "mp": 47,
        "mm": 10,
        "degen": 0
      },
      "E_raw": 0.3466666666666667,
      "sigma": 0.05415478502164643,
      "n_valid": 300,
      "rej_per_step": 0.0
    },
    "N48|even|pi/8": {
      "table": {
        "pp": 190,
        "pm": 40,
        "mp": 54,
        "mm": 16,
        "degen": 0
      },
      "E_raw": 0.37333333333333335,
      "sigma": 0.05356062677695941,
      "n_valid": 300,
      "rej_per_step": 0.0
    },
    "N48|even|pi/4": {
      "table": {
        "pp": 168,
        "pm": 65,
        "mp": 47,
        "mm": 20,
        "degen": 0
      },
      "E_raw": 0.25333333333333335,
      "sigma": 0.05585165536855114,
      "n_valid": 300,
      "rej_per_step": 0.0
    },
    "N48|even|3pi/8": {
      "table": {
        "pp": 158,
        "pm": 78,
        "mp": 36,
        "mm": 28,
        "degen": 0
      },
      "E_raw": 0.24,
      "sigma": 0.0560475988186232,
      "n_valid": 300,
      "rej_per_step": 0.0
    },
    "N48|even|pi/2": {
      "table": {
        "pp": 120,
        "pm": 114,
        "mp": 31,
        "mm": 35,
        "degen": 0
      },
      "E_raw": 0.03333333333333333,
      "sigma": 0.05770294298932793,
      "n_valid": 300,
      "rej_per_step": 5.555555555555555e-07
    },
    "N48|even|5pi/8": {
      "table": {
        "pp": 85,
        "pm": 150,
        "mp": 23,
        "mm": 42,
        "degen": 0
      },
      "E_raw": -0.15333333333333332,
      "sigma": 0.057052282714743004,
      "n_valid": 300,
      "rej_per_step": 0.0
    },
    "N48|even|3pi/4": {
      "table": {
        "pp": 72,
        "pm": 185,
        "mp": 8,
        "mm": 35,
        "degen": 0
      },
      "E_raw": -0.2866666666666667,
      "sigma": 0.055311910176809184,
      "n_valid": 300,
      "rej_per_step": 0.0
    },
    "N48|even|7pi/8": {
      "table": {
        "pp": 55,
        "pm": 184,
        "mp": 13,
        "mm": 48,
        "degen": 0
      },
      "E_raw": -0.31333333333333335,
      "sigma": 0.05482767616882986,
      "n_valid": 300,
      "rej_per_step": 0.0
    },
    "N48|even|pi": {
      "table": {
        "pp": 45,
        "pm": 206,
        "mp": 11,
        "mm": 38,
        "degen": 0
      },
      "E_raw": -0.44666666666666666,
      "sigma": 0.05165555436055542,
      "n_valid": 300,
      "rej_per_step": 0.0
    },
    "N48|odd|0": {
      "table": {
        "pp": 191,
        "pm": 55,
        "mp": 43,
        "mm": 11,
        "degen": 0
      },
      "E_raw": 0.3466666666666667,
      "sigma": 0.05415478502164643,
      "n_valid": 300,
      "rej_per_step": 0.0
    },
    "N48|odd|pi/8": {
      "table": {
        "pp": 185,
        "pm": 56,
        "mp": 46,
        "mm": 13,
        "degen": 0
      },
      "E_raw": 0.32,
      "sigma": 0.05469917732470937,
      "n_valid": 300,
      "rej_per_step": 0.0
    },
    "N48|odd|pi/4": {
      "table": {
        "pp": 180,
        "pm": 57,
        "mp": 45,
        "mm": 18,
        "degen": 0
      },
      "E_raw": 0.32,
      "sigma": 0.05469917732470937,
      "n_valid": 300,
      "rej_per_step": 5.555555555555555e-07
    },
    "N48|odd|3pi/8": {
      "table": {
        "pp": 153,
        "pm": 93,
        "mp": 33,
        "mm": 21,
        "degen": 0
      },
      "E_raw": 0.16,
      "sigma": 0.05699122739510003,
      "n_valid": 300,
      "rej_per_step": 0.0
    },
    "N48|odd|pi/2": {
      "table": {
        "pp": 117,
        "pm": 117,
        "mp": 26,
        "mm": 40,
        "degen": 0
      },
      "E_raw": 0.04666666666666667,
      "sigma": 0.0576721256247251,
      "n_valid": 300,
      "rej_per_step": 5.555555555555555e-07
    },
    "N48|odd|5pi/8": {
      "table": {
        "pp": 95,
        "pm": 140,
        "mp": 28,
        "mm": 37,
        "degen": 0
      },
      "E_raw": -0.12,
      "sigma": 0.0573178273605458,
      "n_valid": 300,
      "rej_per_step": 5.555555555555555e-07
    },
    "N48|odd|3pi/4": {
      "table": {
        "pp": 59,
        "pm": 178,
        "mp": 15,
        "mm": 48,
        "degen": 0
      },
      "E_raw": -0.2866666666666667,
      "sigma": 0.055311910176809184,
      "n_valid": 300,
      "rej_per_step": 0.0
    },
    "N48|odd|7pi/8": {
      "table": {
        "pp": 43,
        "pm": 196,
        "mp": 11,
        "mm": 50,
        "degen": 0
      },
      "E_raw": -0.38,
      "sigma": 0.05340411969127475,
      "n_valid": 300,
      "rej_per_step": 0.0
    },
    "N48|odd|pi": {
      "table": {
        "pp": 52,
        "pm": 181,
        "mp": 14,
        "mm": 53,
        "degen": 0
      },
      "E_raw": -0.3,
      "sigma": 0.055075705472861024,
      "n_valid": 300,
      "rej_per_step": 0.0
    }
  },
  "control_AC": {
    "N48|even|0|A": {
      "table": {
        "pp": 70,
        "pm": 66,
        "mp": 90,
        "mm": 74,
        "degen": 0
      },
      "E_raw": -0.04,
      "sigma": 0.057688820407423826,
      "n_valid": 300,
      "rej_per_step": 0.0
    },
    "N48|even|0|C": {
      "table": {
        "pp": 72,
        "pm": 73,
        "mp": 84,
        "mm": 71,
        "degen": 0
      },
      "E_raw": -0.04666666666666667,
      "sigma": 0.0576721256247251,
      "n_valid": 300,
      "rej_per_step": 0.0
    },
    "N48|even|pi/2|A": {
      "table": {
        "pp": 82,
        "pm": 76,
        "mp": 73,
        "mm": 69,
        "degen": 0
      },
      "E_raw": 0.006666666666666667,
      "sigma": 0.0577337439041085,
      "n_valid": 300,
      "rej_per_step": 0.0
    },
    "N48|even|pi/2|C": {
      "table": {
        "pp": 92,
        "pm": 79,
        "mp": 68,
        "mm": 61,
        "degen": 0
      },
      "E_raw": 0.02,
      "sigma": 0.05772347875864725,
      "n_valid": 300,
      "rej_per_step": 0.0
    },
    "N48|even|pi|A": {
      "table": {
        "pp": 59,
        "pm": 82,
        "mp": 94,
        "mm": 65,
        "degen": 0
      },
      "E_raw": -0.17333333333333334,
      "sigma": 0.056861104326113694,
      "n_valid": 300,
      "rej_per_step": 0.0
    },
    "N48|even|pi|C": {
      "table": {
        "pp": 83,
        "pm": 54,
        "mp": 74,
        "mm": 89,
        "degen": 0
      },
      "E_raw": 0.14666666666666667,
      "sigma": 0.05711067877052092,
      "n_valid": 300,
      "rej_per_step": 0.0
    },
    "N48|odd|0|A": {
      "table": {
        "pp": 67,
        "pm": 88,
        "mp": 70,
        "mm": 75,
        "degen": 0
      },
      "E_raw": -0.05333333333333334,
      "sigma": 0.05765285640670245,
      "n_valid": 300,
      "rej_per_step": 5.555555555555555e-07
    },
    "N48|odd|0|C": {
      "table": {
        "pp": 82,
        "pm": 71,
        "mp": 58,
        "mm": 89,
        "degen": 0
      },
      "E_raw": 0.14,
      "sigma": 0.05716642371182581,
      "n_valid": 300,
      "rej_per_step": 0.0
    },
    "N48|odd|pi/2|A": {
      "table": {
        "pp": 80,
        "pm": 72,
        "mp": 77,
        "mm": 71,
        "degen": 0
      },
      "E_raw": 0.006666666666666667,
      "sigma": 0.0577337439041085,
      "n_valid": 300,
      "rej_per_step": 5.555555555555555e-07
    },
    "N48|odd|pi/2|C": {
      "table": {
        "pp": 76,
        "pm": 71,
        "mp": 77,
        "mm": 76,
        "degen": 0
      },
      "E_raw": 0.013333333333333334,
      "sigma": 0.05772989468846051,
      "n_valid": 300,
      "rej_per_step": 5.555555555555555e-07
    },
    "N48|odd|pi|A": {
      "table": {
        "pp": 71,
        "pm": 75,
        "mp": 87,
        "mm": 67,
        "degen": 0
      },
      "E_raw": -0.08,
      "sigma": 0.05754997827975264,
      "n_valid": 300,
      "rej_per_step": 0.0
    },
    "N48|odd|pi|C": {
      "table": {
        "pp": 68,
        "pm": 88,
        "mp": 66,
        "mm": 78,
        "degen": 0
      },
      "E_raw": -0.02666666666666667,
      "sigma": 0.05771449525866932,
      "n_valid": 300,
      "rej_per_step": 0.0
    }
  },
  "T_low": {
    "N16|even|pi/4": {
      "table": {
        "pp": 182,
        "pm": 59,
        "mp": 48,
        "mm": 11,
        "degen": 0
      },
      "E_raw": 0.2866666666666667,
      "sigma": 0.055311910176809184,
      "n_valid": 300,
      "rej_per_step": 0.0
    },
    "N16|odd|pi/4": {
      "table": {
        "pp": 188,
        "pm": 51,
        "mp": 44,
        "mm": 17,
        "degen": 0
      },
      "E_raw": 0.36666666666666664,
      "sigma": 0.05371391984565254,
      "n_valid": 300,
      "rej_per_step": 0.0
    },
    "N32|even|pi/4": {
      "table": {
        "pp": 181,
        "pm": 68,
        "mp": 36,
        "mm": 15,
        "degen": 0
      },
      "E_raw": 0.30666666666666664,
      "sigma": 0.05495317872381772,
      "n_valid": 300,
      "rej_per_step": 0.0
    },
    "N32|odd|pi/4": {
      "table": {
        "pp": 165,
        "pm": 81,
        "mp": 39,
        "mm": 15,
        "degen": 0
      },
      "E_raw": 0.2,
      "sigma": 0.0565685424949238,
      "n_valid": 300,
      "rej_per_step": 0.0
    },
    "N48|even|pi/4": {
      "table": {
        "pp": 174,
        "pm": 61,
        "mp": 49,
        "mm": 16,
        "degen": 0
      },
      "E_raw": 0.26666666666666666,
      "sigma": 0.05564437344688406,
      "n_valid": 300,
      "rej_per_step": 0.0
    },
    "N48|odd|pi/4": {
      "table": {
        "pp": 176,
        "pm": 63,
        "mp": 38,
        "mm": 23,
        "degen": 0
      },
      "E_raw": 0.32666666666666666,
      "sigma": 0.05456766102399506,
      "n_valid": 300,
      "rej_per_step": 0.0
    }
  },
  "mirror": {
    "N48|odd|0": {
      "E_raw": 0.32666666666666666,
      "E_mirror": 0.32666666666666666,
      "match": true
    },
    "N48|odd|pi/4": {
      "E_raw": 0.3,
      "E_mirror": 0.3,
      "match": true
    },
    "N48|odd|pi/2": {
      "E_raw": 0.013333333333333334,
      "E_mirror": 0.013333333333333334,
      "match": true
    }
  }
}